tests/__init__.py
tests/conftest.py
tests/test_actor.py
tests/test_actor_logic.py
tests/test_actor_state.py
tests/test_config.py
tests/test_path_manager.py
tests/test_processor.py
tests/test_serializer.py
tests/test_stats_processor.py
trieye/__init__.py
trieye/actor.py
trieye/actor_logic.py
trieye/actor_state.py
trieye/config.py
trieye/exceptions.py
trieye/path_manager.py
trieye/schemas.py
trieye/serializer.py
trieye/stats_processor.py
trieye-0.1.5.dist-info/licenses/LICENSE
trieye-0.1.5.dist-info/METADATA
trieye-0.1.5.dist-info/WHEEL
trieye-0.1.5.dist-info/top_level.txt
trieye-0.1.5.dist-info/RECORD
