Metadata-Version: 2.4
Name: trieye
Version: 0.1.5
Summary: Asynchronous statistics collection, processing, logging (MLflow/TensorBoard), and data persistence for ML experiments using Ray.
Author-email: "Luis Guilherme P. M." <lgpelin92@gmail.com>
License: # File: trieye/LICENSE
Project-URL: Homepage, https://github.com/lguibr/trieye
Project-URL: Bug Tracker, https://github.com/lguibr/trieye/issues
Classifier: Programming Language :: Python :: 3
Classifier: Programming Language :: Python :: 3.10
Classifier: Programming Language :: Python :: 3.11
Classifier: License :: OSI Approved :: MIT License
Classifier: Operating System :: OS Independent
Classifier: Topic :: Scientific/Engineering :: Artificial Intelligence
Classifier: Topic :: System :: Logging
Classifier: Topic :: System :: Monitoring
Classifier: Development Status :: 3 - Alpha
Requires-Python: >=3.10
License-File: LICENSE
Requires-Dist: numpy>=1.20.0
Requires-Dist: torch>=2.0.0
Requires-Dist: cloudpickle>=2.0.0
Requires-Dist: mlflow>=1.20.0
Requires-Dist: ray[default]>=2.8.0
Requires-Dist: pydantic>=2.0.0
Requires-Dist: typing_extensions>=4.0.0
Requires-Dist: tensorboard>=2.10.0
Provides-Extra: dev
Requires-Dist: pytest>=7.0.0; extra == "dev"
Requires-Dist: pytest-cov>=3.0.0; extra == "dev"
Requires-Dist: pytest-mock>=3.0.0; extra == "dev"
Requires-Dist: ruff; extra == "dev"
Requires-Dist: mypy; extra == "dev"
Requires-Dist: build; extra == "dev"
Requires-Dist: twine; extra == "dev"
Requires-Dist: codecov; extra == "dev"
Requires-Dist: pytest-xdist; extra == "dev"
Requires-Dist: types-PyYAML; extra == "dev"
Requires-Dist: types-protobuf; extra == "dev"
Dynamic: license-file
